mkdocs_section_index/__init__.py
mkdocs_section_index/plugin.py
mkdocs_section_index/py.typed
mkdocs_section_index/rewrites.py
mkdocs_section_index-0.3.6.dist-info/METADATA
mkdocs_section_index-0.3.6.dist-info/WHEEL
mkdocs_section_index-0.3.6.dist-info/entry_points.txt
mkdocs_section_index-0.3.6.dist-info/licenses/LICENSE.md
mkdocs_section_index-0.3.6.dist-info/RECORD
