Metadata-Version: 2.1
Name: mkdocs-section-index
Version: 0.3.6
Summary: MkDocs plugin to allow clickable sections that lead to an index page
Project-URL: Documentation, https://oprypin.github.io/mkdocs-section-index/
Project-URL: Source, https://github.com/oprypin/mkdocs-section-index
Project-URL: Issues, https://github.com/oprypin/mkdocs-section-index/issues
Project-URL: History, https://github.com/oprypin/mkdocs-section-index/releases
Author-email: Oleh Prypin <oleh@pryp.in>
License-Expression: MIT
License-File: LICENSE.md
Keywords: mkdocs,mkdocs-plugin
Classifier: Development Status :: 5 - Production/Stable
Classifier: Environment :: Console
Classifier: Environment :: Web Environment
Classifier: Intended Audience :: Information Technology
Classifier: License :: OSI Approved :: MIT License
Classifier: Operating System :: OS Independent
Classifier: Programming Language :: Python
Classifier: Programming Language :: Python :: 3.7
Classifier: Programming Language :: Python :: 3.8
Classifier: Programming Language :: Python :: 3.9
Classifier: Programming Language :: Python :: 3.10
Classifier: Programming Language :: Python :: 3.11
Classifier: Topic :: Documentation
Classifier: Topic :: Software Development :: Documentation
Classifier: Topic :: Text Processing :: Markup :: Markdown
Classifier: Typing :: Typed
Requires-Python: >=3.7
Requires-Dist: mkdocs>=1.2
